flask_ignite/__init__.py
flask_ignite/setup_flask_project.py
flask_ignite-0.1.4.dist-info/METADATA
flask_ignite-0.1.4.dist-info/WHEEL
flask_ignite-0.1.4.dist-info/entry_points.txt
flask_ignite-0.1.4.dist-info/top_level.txt
flask_ignite-0.1.4.dist-info/RECORD
