Metadata-Version: 2.1
Name: flask-ignite
Version: 0.1.4
Summary: A simple Flask app creator
Home-page: https://github.com/nahom-d54/flask_admin
Author: Nahom D
Author-email: nahom@nahom.eu.org
License: MIT
Platform: UNKNOWN
Classifier: Programming Language :: Python :: 3
Classifier: License :: OSI Approved :: MIT License
Classifier: Operating System :: OS Independent
Requires-Python: >=3.7
Requires-Dist: flask
Requires-Dist: flask-sqlalchemy
Requires-Dist: flask-migrate
Requires-Dist: python-dotenv
